{
    "_id": "5ea1fffab79ce07a16739ffb",
    "tags": [],
    "colors": [
        "1a1a1a",
        "656565",
        "cccccc",
        "2dc441",
        "27b06b",
        "3e8674",
        "3d6284",
        "8aa3bb",
        "988dbd",
        "8d6dba",
        "9e508d",
        "703c64",
        "be5d79",
        "ce7c46"
    ],
    "downloads": "99",
    "featured": false,
    "likes": 6,
    "comments": 0,
    "title": "Dirty Glass 14",
    "hashtag": "dirtyglass14",
    "description": "",
    "creator": true,
    "slug": "dirty-glass-14",
    "publishedAt": "2020-06-06T22:45:00.012Z",
    "user": {
        "name": "Red Penguin",
        "slug": "red-penguin"
    },
    "numberOfColors": 14,
    "createdAt": "2020-04-23T20:52:10.992Z",
    "isNew": false,
    "sortNewest": false,
    "examples": [],
    "colorsArray": [
        "1a1a1a",
        "656565",
        "cccccc",
        "2dc441",
        "27b06b",
        "3e8674",
        "3d6284",
        "8aa3bb",
        "988dbd",
        "8d6dba",
        "9e508d",
        "703c64",
        "be5d79",
        "ce7c46"
    ],
    "totalPalettes": 2151,
    "minWidth": 14.285714285714286,
    "height": 32,
    "likebutton": {
        "content": "5ea1fffab79ce07a16739ffb",
        "type": "palettes",
        "count": 6,
        "liked": 0
    },
    "thumbnailWidth": null
}