{
    "_id": "5dd54c90bdfa7f3e937fdd98",
    "slug": "cocoa-colors",
    "description": "the color palette for Cocoa\u00a0",
    "colors": [
        "481500",
        "772300",
        "b03300",
        "dd764c",
        "000000",
        "0097ff",
        "00c6ff",
        "61e1ff",
        "c9f4ff",
        "4909e6",
        "2a31ff",
        "3064fc",
        "58b4ff",
        "222222",
        "595959",
        "a5a5a5",
        "d5d5d5",
        "e92356",
        "ff683e",
        "ff9541",
        "ffe67e",
        "00a56d",
        "00ce3c",
        "2eff6b",
        "c8ffa8",
        "7a00ff",
        "bc00ff",
        "f500ff",
        "fe8ae8"
    ],
    "creator": true,
    "comments": 0,
    "likes": 8,
    "createdAt": "2019-11-20T14:24:16.421Z",
    "featured": false,
    "tags": [
        "game"
    ],
    "downloads": "177",
    "numberOfColors": 29,
    "hashtag": "cocoacolors",
    "title": "Cocoa colors ",
    "user": {
        "name": "BluAxolotl",
        "slug": "bluaxolotl"
    },
    "publishedAt": "2020-04-14T17:20:00.018Z",
    "isNew": false,
    "sortNewest": false,
    "examples": [],
    "colorsArray": [
        "481500",
        "772300",
        "b03300",
        "dd764c",
        "000000",
        "0097ff",
        "00c6ff",
        "61e1ff",
        "c9f4ff",
        "4909e6",
        "2a31ff",
        "3064fc",
        "58b4ff",
        "222222",
        "595959",
        "a5a5a5",
        "d5d5d5",
        "e92356",
        "ff683e",
        "ff9541",
        "ffe67e",
        "00a56d",
        "00ce3c",
        "2eff6b",
        "c8ffa8",
        "7a00ff",
        "bc00ff",
        "f500ff",
        "fe8ae8"
    ],
    "totalPalettes": 2151,
    "minWidth": 6.666666666666667,
    "height": 32,
    "likebutton": {
        "content": "5dd54c90bdfa7f3e937fdd98",
        "type": "palettes",
        "count": 8,
        "liked": 0
    },
    "thumbnailWidth": null
}