{
    "_id": "61e2897e976f7b0fec1034b0",
    "tags": [
        "desert",
        "mountains",
        "clouds",
        "cactus",
        "road",
        "dry",
        "mojave"
    ],
    "colors": [
        "dcd1b8",
        "c8b496",
        "aeb0b2",
        "9196a0",
        "60606a",
        "403f4a",
        "38353e",
        "4b444c",
        "79625d",
        "9e8676",
        "be9668",
        "a46848",
        "715a3b",
        "453e2a",
        "3f2926",
        "2e1515",
        "17090c",
        "541e13",
        "d03c32",
        "fba64c"
    ],
    "downloads": "601",
    "featured": false,
    "likes": 48,
    "comments": 1,
    "slug": "mojave20",
    "publishedAt": "2022-01-15T20:45:00.049Z",
    "user": {
        "name": "magodellepercussioni",
        "slug": "magodellepercussioni"
    },
    "title": "mojave20",
    "hashtag": "mojave20",
    "description": "Palette for desertic landscapes, mountains and cloudy skies. Some greens for cacti and bush, yellow/orange for sand and brushland, greys and light blues for skies, clouds and mountains, dark reds and browns for road pavement and tires.\u00a0",
    "creator": true,
    "numberOfColors": 20,
    "createdAt": "2022-01-15T08:44:46.603Z",
    "isNew": false,
    "sortNewest": false,
    "examples": [
        {
            "_id": "61e289c7976f7b0fec1034b7",
            "likes": 0,
            "comments": 0,
            "approval": "approved",
            "title": "mojave20 Palette Example by magodellepercussioni",
            "slug": "mojave20-palette-example-by-magodellepercussionio16wto",
            "publishedAt": "2022-01-15T12:45:00.037Z",
            "user": {
                "name": "magodellepercussioni",
                "slug": "magodellepercussioni"
            },
            "parent": "61e2897e976f7b0fec1034b0",
            "image": "palette-examples/mojave20-palette-example-by-magodellepercussionio16wto.png",
            "creator": true,
            "description": "Examples of use for desert brushland, a truck on the road and cloudy skies.",
            "createdAt": "2022-01-15T08:45:59.209Z",
            "updatedAt": "2022-01-15T12:45:00.037Z",
            "__v": 0,
            "thumbnailOffset": 0,
            "descriptionText": "Examples of use for desert brushland, a truck on the road and cloudy skies."
        }
    ],
    "colorsArray": [
        "dcd1b8",
        "c8b496",
        "aeb0b2",
        "9196a0",
        "60606a",
        "403f4a",
        "38353e",
        "4b444c",
        "79625d",
        "9e8676",
        "be9668",
        "a46848",
        "715a3b",
        "453e2a",
        "3f2926",
        "2e1515",
        "17090c",
        "541e13",
        "d03c32",
        "fba64c"
    ],
    "totalPalettes": 2151,
    "minWidth": 10,
    "height": 32,
    "likebutton": {
        "content": "61e2897e976f7b0fec1034b0",
        "type": "palettes",
        "count": 48,
        "liked": 0
    },
    "thumbnailWidth": 100
}