{
    "_id": "61a0c6e197962a5ef243984e",
    "tags": [],
    "colors": [
        "000000",
        "1e0e2e",
        "222b5f",
        "2c549e",
        "338cca",
        "75dbd1",
        "ffffff",
        "ffeaae",
        "ffb961",
        "ed894e",
        "e95e3f",
        "b4313d",
        "711d43",
        "ae437d",
        "d97484",
        "ab5645",
        "7f4236",
        "472c26",
        "acce38",
        "44a830",
        "1f7f51",
        "1a4f61",
        "453654",
        "645f71",
        "9fa0c8",
        "857995"
    ],
    "downloads": "344",
    "featured": false,
    "likes": 13,
    "comments": 0,
    "slug": "omnia",
    "publishedAt": "2021-12-01T01:00:00.060Z",
    "user": {
        "name": "CopheeMoth",
        "slug": "copheemoth"
    },
    "title": "Omnia",
    "hashtag": "omniapalette",
    "description": "",
    "creator": true,
    "numberOfColors": 26,
    "createdAt": "2021-11-26T11:37:05.944Z",
    "isNew": false,
    "sortNewest": false,
    "examples": [],
    "colorsArray": [
        "000000",
        "1e0e2e",
        "222b5f",
        "2c549e",
        "338cca",
        "75dbd1",
        "ffffff",
        "ffeaae",
        "ffb961",
        "ed894e",
        "e95e3f",
        "b4313d",
        "711d43",
        "ae437d",
        "d97484",
        "ab5645",
        "7f4236",
        "472c26",
        "acce38",
        "44a830",
        "1f7f51",
        "1a4f61",
        "453654",
        "645f71",
        "9fa0c8",
        "857995"
    ],
    "totalPalettes": 2151,
    "minWidth": 7.6923076923076925,
    "height": 32,
    "likebutton": {
        "content": "61a0c6e197962a5ef243984e",
        "type": "palettes",
        "count": 13,
        "liked": 0
    },
    "thumbnailWidth": null
}