{
    "_id": "601e88254781f91d77f98fcf",
    "tags": [
        "artist",
        " goblin",
        " warm",
        " 48",
        " soft"
    ],
    "colors": [
        "000000",
        "140f24",
        "221f3e",
        "34315b",
        "3b486d",
        "4c6589",
        "60839c",
        "7aa2b0",
        "9cbbc1",
        "c0dadc",
        "ffffff",
        "aaf8ff",
        "75d1e4",
        "5aa6bf",
        "5a8cb0",
        "483b6d",
        "66408d",
        "964fad",
        "c26cc9",
        "e089e0",
        "ffc3f0",
        "203040",
        "174646",
        "206437",
        "3a892a",
        "5bb031",
        "9bd32c",
        "cced27",
        "fff15e",
        "ffce3b",
        "e49b35",
        "cc702f",
        "b14926",
        "952008",
        "760811",
        "490a15",
        "2e040f",
        "a00c0c",
        "be3333",
        "d35858",
        "dd9393",
        "581d17",
        "72311b",
        "954f2c",
        "a76b3f",
        "c18c56",
        "dcab7a",
        "edd5a5"
    ],
    "downloads": "2,153",
    "featured": false,
    "likes": 45,
    "comments": 5,
    "title": "GOB-48",
    "hashtag": "gob48",
    "description": "My first palette, warm colours are my personal preference so I thought I may as well make my own colours!",
    "creator": true,
    "slug": "gob-48",
    "publishedAt": "2021-02-09T02:40:00.024Z",
    "user": {
        "name": "Goblin",
        "slug": "goblingamedev"
    },
    "numberOfColors": 48,
    "createdAt": "2021-02-06T12:14:29.928Z",
    "isNew": false,
    "sortNewest": false,
    "examples": [
        {
            "_id": "601e8f164781f91d77f99026",
            "likes": 0,
            "comments": 0,
            "approval": "approved",
            "image": "palette-examples/gob-48-palette-example-by-goblin-commissions-closed-601e8f.png",
            "creator": true,
            "description": "Some small sprites to show off the colours :)",
            "title": "GOB-48 Palette Example by Goblin (Commissions Closed)",
            "slug": "gob-48-palette-example-by-goblin-commissions-closed",
            "publishedAt": "2021-02-06T16:40:00.021Z",
            "user": {
                "name": "Goblin",
                "slug": "goblingamedev"
            },
            "parent": "601e88254781f91d77f98fcf",
            "createdAt": "2021-02-06T12:44:06.982Z",
            "updatedAt": "2021-02-06T16:40:00.021Z",
            "__v": 0,
            "thumbnailOffset": 0,
            "descriptionText": "Some small sprites to show off the colours :)"
        }
    ],
    "colorsArray": [
        "000000",
        "140f24",
        "221f3e",
        "34315b",
        "3b486d",
        "4c6589",
        "60839c",
        "7aa2b0",
        "9cbbc1",
        "c0dadc",
        "ffffff",
        "aaf8ff",
        "75d1e4",
        "5aa6bf",
        "5a8cb0",
        "483b6d",
        "66408d",
        "964fad",
        "c26cc9",
        "e089e0",
        "ffc3f0",
        "203040",
        "174646",
        "206437",
        "3a892a",
        "5bb031",
        "9bd32c",
        "cced27",
        "fff15e",
        "ffce3b",
        "e49b35",
        "cc702f",
        "b14926",
        "952008",
        "760811",
        "490a15",
        "2e040f",
        "a00c0c",
        "be3333",
        "d35858",
        "dd9393",
        "581d17",
        "72311b",
        "954f2c",
        "a76b3f",
        "c18c56",
        "dcab7a",
        "edd5a5"
    ],
    "totalPalettes": 2151,
    "minWidth": 6.25,
    "height": 32,
    "likebutton": {
        "content": "601e88254781f91d77f98fcf",
        "type": "palettes",
        "count": 45,
        "liked": 0
    },
    "thumbnailWidth": 100
}