{
    "_id": "59d8183b0323c15352a71ac3",
    "createdAt": "2017-10-06T23:56:43.809Z",
    "slug": "fun16",
    "description": "1st place winner of the <a href=\"http://http://pixeljoint.com/forum/forum_posts.asp?TID=22582&PN=4\">PixelJoint 16 color palette competition</a> (2015). Created by <a href=\"http://pixeljoint.com/p/23821.htm\">DawnBringer</a>.",
    "colors": [
        "080008",
        "5e6660",
        "2a3443",
        "5d4632",
        "44508c",
        "a6414d",
        "c86b36",
        "8375af",
        "52903c",
        "db7ebd",
        "5b99f4",
        "deac85",
        "94cc4e",
        "84dbfc",
        "f2de70",
        "fcfffe"
    ],
    "tags": [
        "artist",
        "dawnbringer",
        "pjcolorcomp16",
        "pjcolorcomp"
    ],
    "downloads": "351",
    "numberOfColors": 16,
    "comments": 0,
    "likes": 15,
    "hashtag": "fun16",
    "title": "Fun16",
    "publishedAt": "2017-10-06T23:56:43.809Z",
    "isNew": false,
    "sortNewest": false,
    "examples": [],
    "colorsArray": [
        "080008",
        "5e6660",
        "2a3443",
        "5d4632",
        "44508c",
        "a6414d",
        "c86b36",
        "8375af",
        "52903c",
        "db7ebd",
        "5b99f4",
        "deac85",
        "94cc4e",
        "84dbfc",
        "f2de70",
        "fcfffe"
    ],
    "totalPalettes": 2151,
    "minWidth": 12.5,
    "height": 32,
    "likebutton": {
        "content": "59d8183b0323c15352a71ac3",
        "type": "palettes",
        "count": 15,
        "liked": 0
    },
    "thumbnailWidth": null
}