{
    "_id": "61f694e0a4359b1b0fa9689c",
    "tags": [
        "dark",
        "fantasy",
        "medieval",
        "bright",
        "darkfantasy",
        "relaxing"
    ],
    "colors": [
        "6c5c37",
        "61441b",
        "553a27",
        "4d2f21",
        "342310",
        "b68745",
        "9c5d36",
        "6b3114",
        "4a1d15",
        "636a74",
        "3e4c5d",
        "21304e",
        "5d5d34",
        "345534",
        "3e411e",
        "302c21",
        "191620",
        "a29c85",
        "dcdfc6",
        "a5bebc",
        "5f8b86",
        "4b584f",
        "494435",
        "4c383c",
        "000000"
    ],
    "downloads": "227",
    "featured": false,
    "likes": 8,
    "comments": 0,
    "slug": "ty-dark-goon-25",
    "publishedAt": "2022-01-30T17:15:00.055Z",
    "user": {
        "name": "Toby_Yasha",
        "slug": "tobyyasha"
    },
    "title": "TY - Dark Goon 25",
    "hashtag": "darkgoon25",
    "description": "A palette made for when you want your art to have a little bit of a dark and bright aesthetic at the same time.",
    "creator": true,
    "numberOfColors": 25,
    "createdAt": "2022-01-30T13:38:40.233Z",
    "isNew": false,
    "sortNewest": false,
    "examples": [],
    "colorsArray": [
        "6c5c37",
        "61441b",
        "553a27",
        "4d2f21",
        "342310",
        "b68745",
        "9c5d36",
        "6b3114",
        "4a1d15",
        "636a74",
        "3e4c5d",
        "21304e",
        "5d5d34",
        "345534",
        "3e411e",
        "302c21",
        "191620",
        "a29c85",
        "dcdfc6",
        "a5bebc",
        "5f8b86",
        "4b584f",
        "494435",
        "4c383c",
        "000000"
    ],
    "totalPalettes": 2151,
    "minWidth": 7.6923076923076925,
    "height": 32,
    "likebutton": {
        "content": "61f694e0a4359b1b0fa9689c",
        "type": "palettes",
        "count": 8,
        "liked": 0
    },
    "thumbnailWidth": null
}